docco/__init__.py
Docco_CLI-0.0.1.dist-info/METADATA
Docco_CLI-0.0.1.dist-info/WHEEL
Docco_CLI-0.0.1.dist-info/top_level.txt
Docco_CLI-0.0.1.dist-info/RECORD
